pongllm_mcp_demo/__init__.py
pongllm_mcp_demo-0.1.0.dist-info/METADATA
pongllm_mcp_demo-0.1.0.dist-info/WHEEL
pongllm_mcp_demo-0.1.0.dist-info/entry_points.txt
pongllm_mcp_demo-0.1.0.dist-info/RECORD
