Metadata-Version: 2.4
Name: pongllm-mcp-demo
Version: 0.1.0
Summary: Add your description here
Author-email: pong <pongiotdevelop@gmail.com>
Requires-Python: >=3.13
Requires-Dist: mcp[cli]>=1.11.0
